LICENSE
README.md
setup.cfg
setup.py
src/mke_sculib/__init__.py
src/mke_sculib/cam_sensors.py
src/mke_sculib/chan_list_acu.py
src/mke_sculib/dish_checker.py
src/mke_sculib/helpers.py
src/mke_sculib/js_helpers.py
src/mke_sculib/mock_telescope.py
src/mke_sculib/scu.py
src/mke_sculib/sim.py
src/mke_sculib/stellarium_api.py
src/mke_sculib.egg-info/PKG-INFO
src/mke_sculib.egg-info/SOURCES.txt
src/mke_sculib.egg-info/dependency_links.txt
src/mke_sculib.egg-info/requires.txt
src/mke_sculib.egg-info/top_level.txt
tests/test_acu_sim.py
tests/test_scu.py