Metadata-Version: 2.4
Name: mke_sculib
Version: 3.1.1
Summary: MeerKAT Extension (SCU) (lib)rary for the MKE antennas and some basic simulators
Home-page: https://gitlab.mpcdf.mpg.de/tglaubach/mke-sculib
Author: Tobias Glaubach
Author-email: tglaubach@mpifr-bonn.mpg.de
Project-URL: Bug Tracker, https://gitlab.mpcdf.mpg.de/tglaubach/mke-sculib/-/issues
Classifier: License :: OSI Approved :: GNU General Public License v3 or later (GPLv3+)
Classifier: Operating System :: OS Independent
Classifier: Environment :: Console
Classifier: Programming Language :: Python
Classifier: Programming Language :: Python :: 3
Classifier: Programming Language :: Python :: 3 :: Only
Requires-Python: >=3.8
Requires-Dist: requests
Requires-Dist: python-dateutil
Requires-Dist: numpy
Requires-Dist: pandas
Requires-Dist: astropy
Requires-Dist: websockets>=12.0
Requires-Dist: tabulate
